clever_bench/benchmark.py
clever_bench/lean_parser_spec.py
clever_bench/lean_problem.py
clever_bench/setup.py
clever_bench/task.py
clever_bench/lean4/Imports/AllImports.lean
clever_bench/lean4/gitignore
clever_bench/lean4/human_eval/problem_0.lean
clever_bench/lean4/human_eval/problem_1.lean
clever_bench/lean4/human_eval/problem_10.lean
clever_bench/lean4/human_eval/problem_100.lean
clever_bench/lean4/human_eval/problem_101.lean
clever_bench/lean4/human_eval/problem_102.lean
clever_bench/lean4/human_eval/problem_103.lean
clever_bench/lean4/human_eval/problem_104.lean
clever_bench/lean4/human_eval/problem_105.lean
clever_bench/lean4/human_eval/problem_106.lean
clever_bench/lean4/human_eval/problem_107.lean
clever_bench/lean4/human_eval/problem_108.lean
clever_bench/lean4/human_eval/problem_109.lean
clever_bench/lean4/human_eval/problem_11.lean
clever_bench/lean4/human_eval/problem_110.lean
clever_bench/lean4/human_eval/problem_111.lean
clever_bench/lean4/human_eval/problem_112.lean
clever_bench/lean4/human_eval/problem_113.lean
clever_bench/lean4/human_eval/problem_114.lean
clever_bench/lean4/human_eval/problem_115.lean
clever_bench/lean4/human_eval/problem_116.lean
clever_bench/lean4/human_eval/problem_117.lean
clever_bench/lean4/human_eval/problem_118.lean
clever_bench/lean4/human_eval/problem_119.lean
clever_bench/lean4/human_eval/problem_12.lean
clever_bench/lean4/human_eval/problem_120.lean
clever_bench/lean4/human_eval/problem_121.lean
clever_bench/lean4/human_eval/problem_122.lean
clever_bench/lean4/human_eval/problem_123.lean
clever_bench/lean4/human_eval/problem_124.lean
clever_bench/lean4/human_eval/problem_125.lean
clever_bench/lean4/human_eval/problem_126.lean
clever_bench/lean4/human_eval/problem_127.lean
clever_bench/lean4/human_eval/problem_128.lean
clever_bench/lean4/human_eval/problem_129.lean
clever_bench/lean4/human_eval/problem_13.lean
clever_bench/lean4/human_eval/problem_130.lean
clever_bench/lean4/human_eval/problem_131.lean
clever_bench-1.4.0.dist-info/METADATA
clever_bench-1.4.0.dist-info/WHEEL
clever_bench-1.4.0.dist-info/entry_points.txt
clever_bench-1.4.0.dist-info/licenses/LICENSE
clever_bench-1.4.0.dist-info/RECORD
