Metadata-Version: 2.4
Name: clever-bench
Version: 1.4.0
Summary: Python library for running the CLEVER Benchmark
Project-URL: Homepage, https://github.com/trishullab/clever-bench
Project-URL: Issues, https://github.com/trishullab/clever/issues
Author-email: Amitayush Thakur <amitayush@utexas.edu>
License-File: LICENSE
Classifier: License :: OSI Approved :: MIT License
Classifier: Operating System :: POSIX :: Linux
Classifier: Programming Language :: Python :: 3
Requires-Python: >=3.9
Requires-Dist: pyyaml>=6.0
